<?xml version="1.0" encoding="utf-8"?>
<extension type="component" version="3.2.0" method="upgrade">

	<name>shooting_event</name>
	<creationDate>December 2017</creationDate>
	<author>Magnus Linell</author>
	<license>MIT</license>
	<version>0.0.2</version>
	<description>Shooting Event Component</description>

	<!-- Site files -->
	<files folder="site">
		<filename>index.html</filename>
		<filename>shooting_event.php</filename>
		<filename>shooting_event_list.php</filename>
		<filename>shooting_event_read.php</filename>
		<filename>shooting_event_save.php</filename>
	</files>

	<!-- Admin files -->
	<administration>
		<menu link='index.php?option=com_shooting_event'>Events - redigera</menu>
		<files folder="admin">
			<filename>index.html</filename>
			<filename>shooting_event.php</filename>
		</files>
	</administration>

</extension>
